Metadata-Version: 2.1
Name: ml-group-model
Version: 0.0.1
Summary: A model for the ml group
Author: Mirko
